kat_transform/__init__.py
kat_transform/exceptions.py
kat_transform/field.py
kat_transform/markers.py
kat_transform/metadata.py
kat_transform/py.typed
kat_transform/resolve_fields.py
kat_transform/schema.py
kat_transform/util.py
kat_transform-0.0.6.dist-info/METADATA
kat_transform-0.0.6.dist-info/WHEEL
kat_transform-0.0.6.dist-info/licenses/LICENSE.md
kat_transform-0.0.6.dist-info/RECORD
