Metadata-Version: 2.4
Name: kat-transform
Version: 0.0.6
Summary: Transform python data using declarative schemas
Project-URL: homepage, https://github.com/KuyuCode/kat-transform
Author-email: kuyugama <mail.kuyugama@gmail.com>
License-File: LICENSE.md
Classifier: Programming Language :: Python :: 3
Requires-Python: >=3.10
Requires-Dist: fundi>=1.2.2
